[
  {
    "id": 1,
    "Test": "outputs/libkluzzer/iaed_p1/135/test-suite/fuzzer1665682965363875011_1.xml",
    "Coverage (individual)": 0,
    "Coverage (accumulated)": 0.0,
    "Execution success": false,
    "Returncode": -9,
    "CPU-Time (s)": 4.003011029,
    "Wall-Time (s)": 4.005046478938311,
    "Memory used (byte)": 245760
  },
  {
    "id": 2,
    "Test": "outputs/libkluzzer/iaed_p1/135/test-suite/fuzzer1665682966370735545_1.xml",
    "Coverage (individual)": 0,
    "Coverage (accumulated)": 0.0,
    "Execution success": false,
    "Returncode": -9,
    "CPU-Time (s)": 4.001934918,
    "Wall-Time (s)": 4.007791709620506,
    "Memory used (byte)": 299008
  }
]