[
  {
    "id": 1,
    "Test": "outputs/FuSeBMC/iaed_p2/25/test-suite/Testcase_128_Fu.xml",
    "Coverage (individual)": 0,
    "Coverage (accumulated)": 0.0,
    "Execution success": false,
    "Returncode": -9,
    "CPU-Time (s)": 4.01577418,
    "Wall-Time (s)": 4.018226336222142,
    "Memory used (byte)": 245760
  },
  {
    "id": 2,
    "Test": "outputs/FuSeBMC/iaed_p2/25/test-suite/Testcase_134_Fu.xml",
    "Coverage (individual)": 0,
    "Coverage (accumulated)": 0.0,
    "Execution success": false,
    "Returncode": -9,
    "CPU-Time (s)": 4.01064813,
    "Wall-Time (s)": 4.012964349240065,
    "Memory used (byte)": 245760
  },
  {
    "id": 3,
    "Test": "outputs/FuSeBMC/iaed_p2/25/test-suite/Testcase_131_Fu.xml",
    "Coverage (individual)": 0,
    "Coverage (accumulated)": 0.0,
    "Execution success": false,
    "Returncode": -9,
    "CPU-Time (s)": 4.000067266,
    "Wall-Time (s)": 4.003081761300564,
    "Memory used (byte)": 245760
  },
  {
    "id": 4,
    "Test": "outputs/FuSeBMC/iaed_p2/25/test-suite/Testcase_129_Fu.xml",
    "Coverage (individual)": 0,
    "Coverage (accumulated)": 0.0,
    "Execution success": false,
    "Returncode": -9,
    "CPU-Time (s)": 4.001074374,
    "Wall-Time (s)": 4.00432937592268,
    "Memory used (byte)": 245760
  },
  {
    "id": 5,
    "Test": "outputs/FuSeBMC/iaed_p2/25/test-suite/Testcase_133_Fu.xml",
    "Coverage (individual)": 0,
    "Coverage (accumulated)": 0.0,
    "Execution success": false,
    "Returncode": -9,
    "CPU-Time (s)": 4.001960642,
    "Wall-Time (s)": 4.004783506970853,
    "Memory used (byte)": 245760
  },
  {
    "id": 6,
    "Test": "outputs/FuSeBMC/iaed_p2/25/test-suite/Testcase_132_Fu.xml",
    "Coverage (individual)": 0,
    "Coverage (accumulated)": 0.0,
    "Execution success": false,
    "Returncode": -9,
    "CPU-Time (s)": 3.998739728,
    "Wall-Time (s)": 4.004248893819749,
    "Memory used (byte)": 253952
  },
  {
    "id": 7,
    "Test": "outputs/FuSeBMC/iaed_p2/25/test-suite/FUZ_OcnumfOIeh9vVqY2gvms_117.xml",
    "Coverage (individual)": 0,
    "Coverage (accumulated)": 0.0,
    "Execution success": false,
    "Returncode": -9,
    "CPU-Time (s)": 3.999911108,
    "Wall-Time (s)": 4.003284583799541,
    "Memory used (byte)": 245760
  },
  {
    "id": 8,
    "Test": "outputs/FuSeBMC/iaed_p2/25/test-suite/Testcase_130_Fu.xml",
    "Coverage (individual)": 0,
    "Coverage (accumulated)": 0.0,
    "Execution success": false,
    "Returncode": -9,
    "CPU-Time (s)": 3.999782196,
    "Wall-Time (s)": 4.004644053056836,
    "Memory used (byte)": 299008
  }
]