[
  {
    "id": 1,
    "Test": "outputs/libkluzzer/iaed_p1/132/test-suite/fuzzer1665681153232582041_1.xml",
    "Coverage (individual)": 0,
    "Coverage (accumulated)": 0.0,
    "Execution success": false,
    "Returncode": -9,
    "CPU-Time (s)": 4.003923773,
    "Wall-Time (s)": 4.006166120059788,
    "Memory used (byte)": 1032192
  },
  {
    "id": 2,
    "Test": "outputs/libkluzzer/iaed_p1/132/test-suite/fuzzer1665681152220478963_1.xml",
    "Coverage (individual)": 0,
    "Coverage (accumulated)": 0.0,
    "Execution success": false,
    "Returncode": -9,
    "CPU-Time (s)": 4.000920342,
    "Wall-Time (s)": 4.003017066046596,
    "Memory used (byte)": 1032192
  }
]