[
  {
    "id": 1,
    "Test": "outputs/symbiotic/asa_1819_p2/al113/test000001.2.xml",
    "Coverage (individual)": 0.0,
    "Coverage (accumulated)": 0.0,
    "Execution success": true,
    "Returncode": 1,
    "CPU-Time (s)": 0.002825465,
    "Wall-Time (s)": 0.004615540150552988,
    "Memory used (byte)": 245760
  },
  {
    "id": 2,
    "Test": "outputs/symbiotic/asa_1819_p2/al113/test000001.3.xml",
    "Coverage (individual)": 0.0,
    "Coverage (accumulated)": 0.0,
    "Execution success": true,
    "Returncode": 1,
    "CPU-Time (s)": 0.002763796,
    "Wall-Time (s)": 0.007361208088696003,
    "Memory used (byte)": 245760
  },
  {
    "id": 3,
    "Test": "outputs/symbiotic/asa_1819_p2/al113/test000001.12.xml",
    "Coverage (individual)": 0.0,
    "Coverage (accumulated)": 0.0,
    "Execution success": true,
    "Returncode": 1,
    "CPU-Time (s)": 0.002884203,
    "Wall-Time (s)": 0.005927405785769224,
    "Memory used (byte)": 245760
  },
  {
    "id": 4,
    "Test": "outputs/symbiotic/asa_1819_p2/al113/test000001.xml",
    "Coverage (individual)": 0,
    "Coverage (accumulated)": 0.0,
    "Execution success": false,
    "Returncode": -11,
    "CPU-Time (s)": 0.002856921,
    "Wall-Time (s)": 0.2853360972367227,
    "Memory used (byte)": 376832
  },
  {
    "id": 5,
    "Test": "outputs/symbiotic/asa_1819_p2/al113/test000001.8.xml",
    "Coverage (individual)": 0.0,
    "Coverage (accumulated)": 0.0,
    "Execution success": true,
    "Returncode": 1,
    "CPU-Time (s)": 0.002913364,
    "Wall-Time (s)": 0.004507058300077915,
    "Memory used (byte)": 245760
  },
  {
    "id": 6,
    "Test": "outputs/symbiotic/asa_1819_p2/al113/test000001.7.xml",
    "Coverage (individual)": 0.0,
    "Coverage (accumulated)": 0.0,
    "Execution success": true,
    "Returncode": 1,
    "CPU-Time (s)": 0.002325413,
    "Wall-Time (s)": 0.004079089034348726,
    "Memory used (byte)": 245760
  },
  {
    "id": 7,
    "Test": "outputs/symbiotic/asa_1819_p2/al113/test000001.9.xml",
    "Coverage (individual)": 0.0,
    "Coverage (accumulated)": 0.0,
    "Execution success": true,
    "Returncode": 1,
    "CPU-Time (s)": 0.00261858,
    "Wall-Time (s)": 0.005977013148367405,
    "Memory used (byte)": 245760
  },
  {
    "id": 8,
    "Test": "outputs/symbiotic/asa_1819_p2/al113/test000001.11.xml",
    "Coverage (individual)": 0.0,
    "Coverage (accumulated)": 0.0,
    "Execution success": true,
    "Returncode": 1,
    "CPU-Time (s)": 0.001690495,
    "Wall-Time (s)": 0.005790637340396643,
    "Memory used (byte)": 245760
  },
  {
    "id": 9,
    "Test": "outputs/symbiotic/asa_1819_p2/al113/test000001.1.xml",
    "Coverage (individual)": 0.0,
    "Coverage (accumulated)": 0.0,
    "Execution success": true,
    "Returncode": 1,
    "CPU-Time (s)": 0.002261675,
    "Wall-Time (s)": 0.006342246662825346,
    "Memory used (byte)": 245760
  },
  {
    "id": 10,
    "Test": "outputs/symbiotic/asa_1819_p2/al113/test000001.5.xml",
    "Coverage (individual)": 0.0,
    "Coverage (accumulated)": 0.0,
    "Execution success": true,
    "Returncode": 1,
    "CPU-Time (s)": 0.003788451,
    "Wall-Time (s)": 0.005389568395912647,
    "Memory used (byte)": 245760
  },
  {
    "id": 11,
    "Test": "outputs/symbiotic/asa_1819_p2/al113/test000001.10.xml",
    "Coverage (individual)": 0.0,
    "Coverage (accumulated)": 0.0,
    "Execution success": true,
    "Returncode": 1,
    "CPU-Time (s)": 0.003231247,
    "Wall-Time (s)": 0.004995911847800016,
    "Memory used (byte)": 245760
  },
  {
    "id": 12,
    "Test": "outputs/symbiotic/asa_1819_p2/al113/test000001.14.xml",
    "Coverage (individual)": 0.0,
    "Coverage (accumulated)": 0.0,
    "Execution success": true,
    "Returncode": 1,
    "CPU-Time (s)": 0.001647376,
    "Wall-Time (s)": 0.005697519052773714,
    "Memory used (byte)": 245760
  },
  {
    "id": 13,
    "Test": "outputs/symbiotic/asa_1819_p2/al113/test000001.6.xml",
    "Coverage (individual)": 0.0,
    "Coverage (accumulated)": 0.0,
    "Execution success": true,
    "Returncode": 1,
    "CPU-Time (s)": 0.003054388,
    "Wall-Time (s)": 0.00484418123960495,
    "Memory used (byte)": 245760
  },
  {
    "id": 14,
    "Test": "outputs/symbiotic/asa_1819_p2/al113/test000001.15.xml",
    "Coverage (individual)": 0.0,
    "Coverage (accumulated)": 0.0,
    "Execution success": true,
    "Returncode": 1,
    "CPU-Time (s)": 0.002480491,
    "Wall-Time (s)": 0.0055358619429171085,
    "Memory used (byte)": 245760
  },
  {
    "id": 15,
    "Test": "outputs/symbiotic/asa_1819_p2/al113/test000001.0.xml",
    "Coverage (individual)": 0.0,
    "Coverage (accumulated)": 0.0,
    "Execution success": true,
    "Returncode": 1,
    "CPU-Time (s)": 0.002545997,
    "Wall-Time (s)": 0.005225662142038345,
    "Memory used (byte)": 245760
  },
  {
    "id": 16,
    "Test": "outputs/symbiotic/asa_1819_p2/al113/test000001.16.xml",
    "Coverage (individual)": 0.0,
    "Coverage (accumulated)": 0.0,
    "Execution success": true,
    "Returncode": 1,
    "CPU-Time (s)": 0.003592102,
    "Wall-Time (s)": 0.005213342607021332,
    "Memory used (byte)": 245760
  },
  {
    "id": 17,
    "Test": "outputs/symbiotic/asa_1819_p2/al113/test000001.4.xml",
    "Coverage (individual)": 0.0,
    "Coverage (accumulated)": 0.0,
    "Execution success": true,
    "Returncode": 1,
    "CPU-Time (s)": 0.00343355,
    "Wall-Time (s)": 0.005400790832936764,
    "Memory used (byte)": 245760
  }
]