[
  {
    "id": 1,
    "Test": "outputs/CPAchecker/iaed_p1/63/test-suite/testcase3.xml",
    "Coverage (individual)": 0,
    "Coverage (accumulated)": 0.0,
    "Execution success": false,
    "Returncode": -9,
    "CPU-Time (s)": 4.002798403,
    "Wall-Time (s)": 4.007356057874858,
    "Memory used (byte)": 278528
  },
  {
    "id": 2,
    "Test": "outputs/CPAchecker/iaed_p1/63/test-suite/testcase5.xml",
    "Coverage (individual)": 0,
    "Coverage (accumulated)": 0.0,
    "Execution success": false,
    "Returncode": -9,
    "CPU-Time (s)": 4.002009125,
    "Wall-Time (s)": 4.004955753218383,
    "Memory used (byte)": 245760
  },
  {
    "id": 3,
    "Test": "outputs/CPAchecker/iaed_p1/63/test-suite/testcase6.xml",
    "Coverage (individual)": 0,
    "Coverage (accumulated)": 0.0,
    "Execution success": false,
    "Returncode": -9,
    "CPU-Time (s)": 4.023189807,
    "Wall-Time (s)": 4.025582287926227,
    "Memory used (byte)": 245760
  },
  {
    "id": 4,
    "Test": "outputs/CPAchecker/iaed_p1/63/test-suite/testcase7.xml",
    "Coverage (individual)": 0,
    "Coverage (accumulated)": 0.0,
    "Execution success": false,
    "Returncode": -9,
    "CPU-Time (s)": 4.002413148,
    "Wall-Time (s)": 4.005247630178928,
    "Memory used (byte)": 245760
  },
  {
    "id": 5,
    "Test": "outputs/CPAchecker/iaed_p1/63/test-suite/testcase8.xml",
    "Coverage (individual)": 0,
    "Coverage (accumulated)": 0.0,
    "Execution success": false,
    "Returncode": -9,
    "CPU-Time (s)": 4.001742674,
    "Wall-Time (s)": 4.00390979507938,
    "Memory used (byte)": 245760
  },
  {
    "id": 6,
    "Test": "outputs/CPAchecker/iaed_p1/63/test-suite/testcase4.xml",
    "Coverage (individual)": 0,
    "Coverage (accumulated)": 0.0,
    "Execution success": false,
    "Returncode": -9,
    "CPU-Time (s)": 4.008401727,
    "Wall-Time (s)": 4.014478126075119,
    "Memory used (byte)": 299008
  },
  {
    "id": 7,
    "Test": "outputs/CPAchecker/iaed_p1/63/test-suite/testcase9.xml",
    "Coverage (individual)": 0,
    "Coverage (accumulated)": 0.0,
    "Execution success": false,
    "Returncode": -9,
    "CPU-Time (s)": 4.001471793,
    "Wall-Time (s)": 4.0040970160625875,
    "Memory used (byte)": 245760
  },
  {
    "id": 8,
    "Test": "outputs/CPAchecker/iaed_p1/63/test-suite/testcase0.xml",
    "Coverage (individual)": 0,
    "Coverage (accumulated)": 0.0,
    "Execution success": false,
    "Returncode": -9,
    "CPU-Time (s)": 4.000568382,
    "Wall-Time (s)": 4.004292631987482,
    "Memory used (byte)": 286720
  },
  {
    "id": 9,
    "Test": "outputs/CPAchecker/iaed_p1/63/test-suite/testcase1.xml",
    "Coverage (individual)": 0,
    "Coverage (accumulated)": 0.0,
    "Execution success": false,
    "Returncode": -9,
    "CPU-Time (s)": 4.007264088,
    "Wall-Time (s)": 4.00995552027598,
    "Memory used (byte)": 245760
  },
  {
    "id": 10,
    "Test": "outputs/CPAchecker/iaed_p1/63/test-suite/testcase2.xml",
    "Coverage (individual)": 0,
    "Coverage (accumulated)": 0.0,
    "Execution success": false,
    "Returncode": -9,
    "CPU-Time (s)": 4.018335813,
    "Wall-Time (s)": 4.020966747775674,
    "Memory used (byte)": 245760
  }
]