[
    {
        "bug_type": "  accessing out of bounds index",
        "line": 549,
        "procedure": "unknown",
        "file": "proj_1.c"
    },
    {
        "bug_type": "  accessing out of bounds index",
        "line": 549,
        "procedure": "unknown",
        "file": "proj_1.c"
    },
    {
        "bug_type": "  function memcpy: precondition 'valid_src' got status invalid",
        "line": 622,
        "procedure": "unknown",
        "file": "proj_1.c"
    },
    {
        "bug_type": "  accessing out of bounds index",
        "line": 130,
        "procedure": "unknown",
        "file": "proj_1.c"
    },
    {
        "bug_type": "  accessing out of bounds index",
        "line": 130,
        "procedure": "unknown",
        "file": "proj_1.c"
    },
    {
        "bug_type": "  accessing out of bounds index",
        "line": 217,
        "procedure": "unknown",
        "file": "proj_1.c"
    },
    {
        "bug_type": "  accessing out of bounds index",
        "line": 246,
        "procedure": "unknown",
        "file": "proj_1.c"
    },
    {
        "bug_type": "  accessing out of bounds index",
        "line": 269,
        "procedure": "unknown",
        "file": "proj_1.c"
    },
    {
        "bug_type": "  accessing out of bounds index",
        "line": 424,
        "procedure": "unknown",
        "file": "proj_1.c"
    },
    {
        "bug_type": "  accessing out of bounds index",
        "line": 338,
        "procedure": "unknown",
        "file": "proj_1.c"
    },
    {
        "bug_type": "  function printf_va_2: precondition valid_read_string(param0) got status unknown",
        "line": 74,
        "procedure": "unknown",
        "file": "proj_1.c"
    },
    {
        "bug_type": "  function printf_va_24: precondition valid_read_string(param0) got status unknown",
        "line": 522,
        "procedure": "unknown",
        "file": "proj_1.c"
    },
    {
        "bug_type": "  function memcpy: precondition 'valid_src' got status unknown",
        "line": 622,
        "procedure": "unknown",
        "file": "proj_1.c"
    },
    {
        "bug_type": "  accessing out of bounds index",
        "line": 625,
        "procedure": "unknown",
        "file": "proj_1.c"
    },
    {
        "bug_type": "  accessing out of bounds index",
        "line": 145,
        "procedure": "unknown",
        "file": "proj_1.c"
    },
    {
        "bug_type": "  signed overflow",
        "line": 151,
        "procedure": "unknown",
        "file": "proj_1.c"
    },
    {
        "bug_type": "  signed overflow",
        "line": 151,
        "procedure": "unknown",
        "file": "proj_1.c"
    },
    {
        "bug_type": "  signed overflow",
        "line": 158,
        "procedure": "unknown",
        "file": "proj_1.c"
    },
    {
        "bug_type": "  signed overflow",
        "line": 158,
        "procedure": "unknown",
        "file": "proj_1.c"
    },
    {
        "bug_type": "  accessing uninitialized left-value",
        "line": 175,
        "procedure": "unknown",
        "file": "proj_1.c"
    },
    {
        "bug_type": "  signed overflow",
        "line": 188,
        "procedure": "unknown",
        "file": "proj_1.c"
    },
    {
        "bug_type": "  signed overflow",
        "line": 188,
        "procedure": "unknown",
        "file": "proj_1.c"
    },
    {
        "bug_type": "  function printf_va_12: precondition valid_read_string(param0) got status unknown",
        "line": 226,
        "procedure": "unknown",
        "file": "proj_1.c"
    },
    {
        "bug_type": "  signed overflow",
        "line": 246,
        "procedure": "unknown",
        "file": "proj_1.c"
    },
    {
        "bug_type": "  signed overflow",
        "line": 246,
        "procedure": "unknown",
        "file": "proj_1.c"
    },
    {
        "bug_type": "  signed overflow",
        "line": 270,
        "procedure": "unknown",
        "file": "proj_1.c"
    },
    {
        "bug_type": "  signed overflow",
        "line": 270,
        "procedure": "unknown",
        "file": "proj_1.c"
    },
    {
        "bug_type": "  signed overflow",
        "line": 276,
        "procedure": "unknown",
        "file": "proj_1.c"
    },
    {
        "bug_type": "  signed overflow",
        "line": 276,
        "procedure": "unknown",
        "file": "proj_1.c"
    },
    {
        "bug_type": "  accessing uninitialized left-value",
        "line": 550,
        "procedure": "unknown",
        "file": "proj_1.c"
    },
    {
        "bug_type": "  accessing uninitialized left-value",
        "line": 550,
        "procedure": "unknown",
        "file": "proj_1.c"
    },
    {
        "bug_type": "  function printf_va_28: precondition valid_read_string(param0) got status unknown",
        "line": 550,
        "procedure": "unknown",
        "file": "proj_1.c"
    },
    {
        "bug_type": "  signed overflow",
        "line": 473,
        "procedure": "unknown",
        "file": "proj_1.c"
    },
    {
        "bug_type": "  out of bounds read",
        "line": 475,
        "procedure": "unknown",
        "file": "proj_1.c"
    },
    {
        "bug_type": "  signed overflow",
        "line": 480,
        "procedure": "unknown",
        "file": "proj_1.c"
    },
    {
        "bug_type": "  out of bounds read",
        "line": 482,
        "procedure": "unknown",
        "file": "proj_1.c"
    },
    {
        "bug_type": "  accessing uninitialized left-value",
        "line": 472,
        "procedure": "unknown",
        "file": "proj_1.c"
    },
    {
        "bug_type": "  accessing uninitialized left-value",
        "line": 479,
        "procedure": "unknown",
        "file": "proj_1.c"
    },
    {
        "bug_type": "  signed overflow",
        "line": 487,
        "procedure": "unknown",
        "file": "proj_1.c"
    },
    {
        "bug_type": "  out of bounds read",
        "line": 487,
        "procedure": "unknown",
        "file": "proj_1.c"
    },
    {
        "bug_type": "  accessing uninitialized left-value",
        "line": 522,
        "procedure": "unknown",
        "file": "proj_1.c"
    },
    {
        "bug_type": "  accessing uninitialized left-value",
        "line": 522,
        "procedure": "unknown",
        "file": "proj_1.c"
    },
    {
        "bug_type": "  accessing uninitialized left-value",
        "line": 632,
        "procedure": "unknown",
        "file": "proj_1.c"
    },
    {
        "bug_type": "  accessing uninitialized left-value",
        "line": 632,
        "procedure": "unknown",
        "file": "proj_1.c"
    },
    {
        "bug_type": "  function printf_va_31: precondition valid_read_string(param0) got status unknown",
        "line": 632,
        "procedure": "unknown",
        "file": "proj_1.c"
    },
    {
        "bug_type": "  signed overflow",
        "line": 151,
        "procedure": "unknown",
        "file": "proj_1.c"
    },
    {
        "bug_type": "  signed overflow",
        "line": 151,
        "procedure": "unknown",
        "file": "proj_1.c"
    },
    {
        "bug_type": "  signed overflow",
        "line": 158,
        "procedure": "unknown",
        "file": "proj_1.c"
    },
    {
        "bug_type": "  signed overflow",
        "line": 158,
        "procedure": "unknown",
        "file": "proj_1.c"
    },
    {
        "bug_type": "  accessing uninitialized left-value",
        "line": 163,
        "procedure": "unknown",
        "file": "proj_1.c"
    },
    {
        "bug_type": "  accessing uninitialized left-value",
        "line": 164,
        "procedure": "unknown",
        "file": "proj_1.c"
    },
    {
        "bug_type": "  signed overflow",
        "line": 164,
        "procedure": "unknown",
        "file": "proj_1.c"
    },
    {
        "bug_type": "  signed overflow",
        "line": 164,
        "procedure": "unknown",
        "file": "proj_1.c"
    },
    {
        "bug_type": "  signed overflow",
        "line": 165,
        "procedure": "unknown",
        "file": "proj_1.c"
    },
    {
        "bug_type": "  signed overflow",
        "line": 165,
        "procedure": "unknown",
        "file": "proj_1.c"
    },
    {
        "bug_type": "  accessing uninitialized left-value",
        "line": 219,
        "procedure": "unknown",
        "file": "proj_1.c"
    },
    {
        "bug_type": "  accessing uninitialized left-value",
        "line": 220,
        "procedure": "unknown",
        "file": "proj_1.c"
    },
    {
        "bug_type": "  function printf_va_11: precondition valid_read_string(param0) got status unknown",
        "line": 220,
        "procedure": "unknown",
        "file": "proj_1.c"
    },
    {
        "bug_type": "  accessing uninitialized left-value",
        "line": 426,
        "procedure": "unknown",
        "file": "proj_1.c"
    },
    {
        "bug_type": "  accessing out of bounds index",
        "line": 438,
        "procedure": "unknown",
        "file": "proj_1.c"
    },
    {
        "bug_type": "  accessing uninitialized left-value",
        "line": 438,
        "procedure": "unknown",
        "file": "proj_1.c"
    },
    {
        "bug_type": "  signed overflow",
        "line": 438,
        "procedure": "unknown",
        "file": "proj_1.c"
    },
    {
        "bug_type": "  signed overflow",
        "line": 438,
        "procedure": "unknown",
        "file": "proj_1.c"
    },
    {
        "bug_type": "  accessing uninitialized left-value",
        "line": 440,
        "procedure": "unknown",
        "file": "proj_1.c"
    },
    {
        "bug_type": "  accessing uninitialized left-value",
        "line": 440,
        "procedure": "unknown",
        "file": "proj_1.c"
    },
    {
        "bug_type": "  signed overflow",
        "line": 440,
        "procedure": "unknown",
        "file": "proj_1.c"
    },
    {
        "bug_type": "  signed overflow",
        "line": 440,
        "procedure": "unknown",
        "file": "proj_1.c"
    },
    {
        "bug_type": "  signed overflow",
        "line": 440,
        "procedure": "unknown",
        "file": "proj_1.c"
    },
    {
        "bug_type": "  signed overflow",
        "line": 440,
        "procedure": "unknown",
        "file": "proj_1.c"
    },
    {
        "bug_type": "  accessing out of bounds index",
        "line": 454,
        "procedure": "unknown",
        "file": "proj_1.c"
    },
    {
        "bug_type": "  accessing uninitialized left-value",
        "line": 313,
        "procedure": "unknown",
        "file": "proj_1.c"
    },
    {
        "bug_type": "  accessing uninitialized left-value",
        "line": 339,
        "procedure": "unknown",
        "file": "proj_1.c"
    },
    {
        "bug_type": "  accessing uninitialized left-value",
        "line": 339,
        "procedure": "unknown",
        "file": "proj_1.c"
    },
    {
        "bug_type": "  signed overflow",
        "line": 339,
        "procedure": "unknown",
        "file": "proj_1.c"
    },
    {
        "bug_type": "  signed overflow",
        "line": 339,
        "procedure": "unknown",
        "file": "proj_1.c"
    },
    {
        "bug_type": "  signed overflow",
        "line": 339,
        "procedure": "unknown",
        "file": "proj_1.c"
    },
    {
        "bug_type": "  signed overflow",
        "line": 339,
        "procedure": "unknown",
        "file": "proj_1.c"
    },
    {
        "bug_type": "  accessing uninitialized left-value",
        "line": 373,
        "procedure": "unknown",
        "file": "proj_1.c"
    },
    {
        "bug_type": "  accessing uninitialized left-value",
        "line": 375,
        "procedure": "unknown",
        "file": "proj_1.c"
    },
    {
        "bug_type": "  accessing out of bounds index",
        "line": 550,
        "procedure": "unknown",
        "file": "proj_1.c"
    },
    {
        "bug_type": "  accessing uninitialized left-value",
        "line": 478,
        "procedure": "unknown",
        "file": "proj_1.c"
    },
    {
        "bug_type": "  out of bounds read",
        "line": 562,
        "procedure": "unknown",
        "file": "proj_1.c"
    },
    {
        "bug_type": "  function strcmp: precondition 'valid_string_s1' got status unknown",
        "line": 566,
        "procedure": "unknown",
        "file": "proj_1.c"
    },
    {
        "bug_type": "  function strcmp: precondition 'valid_string_s2' got status unknown",
        "line": 566,
        "procedure": "unknown",
        "file": "proj_1.c"
    },
    {
        "bug_type": "  function strcmp: precondition 'valid_string_s1' got status unknown",
        "line": 573,
        "procedure": "unknown",
        "file": "proj_1.c"
    },
    {
        "bug_type": "  function strcmp: precondition 'valid_string_s2' got status unknown",
        "line": 573,
        "procedure": "unknown",
        "file": "proj_1.c"
    },
    {
        "bug_type": "  accessing uninitialized left-value",
        "line": 574,
        "procedure": "unknown",
        "file": "proj_1.c"
    },
    {
        "bug_type": "  accessing uninitialized left-value",
        "line": 574,
        "procedure": "unknown",
        "file": "proj_1.c"
    },
    {
        "bug_type": "  signed overflow",
        "line": 567,
        "procedure": "unknown",
        "file": "proj_1.c"
    },
    {
        "bug_type": "  out of bounds read",
        "line": 569,
        "procedure": "unknown",
        "file": "proj_1.c"
    },
    {
        "bug_type": "  signed overflow",
        "line": 575,
        "procedure": "unknown",
        "file": "proj_1.c"
    },
    {
        "bug_type": "  out of bounds read",
        "line": 577,
        "procedure": "unknown",
        "file": "proj_1.c"
    },
    {
        "bug_type": "  signed overflow",
        "line": 585,
        "procedure": "unknown",
        "file": "proj_1.c"
    },
    {
        "bug_type": "  out of bounds read",
        "line": 585,
        "procedure": "unknown",
        "file": "proj_1.c"
    },
    {
        "bug_type": "  accessing out of bounds index",
        "line": 632,
        "procedure": "unknown",
        "file": "proj_1.c"
    },
    {
        "bug_type": "  accessing out of bounds index",
        "line": 163,
        "procedure": "unknown",
        "file": "proj_1.c"
    },
    {
        "bug_type": "  accessing out of bounds index",
        "line": 182,
        "procedure": "unknown",
        "file": "proj_1.c"
    },
    {
        "bug_type": "  accessing out of bounds index",
        "line": 182,
        "procedure": "unknown",
        "file": "proj_1.c"
    },
    {
        "bug_type": "  accessing uninitialized left-value",
        "line": 185,
        "procedure": "unknown",
        "file": "proj_1.c"
    },
    {
        "bug_type": "  signed overflow",
        "line": 185,
        "procedure": "unknown",
        "file": "proj_1.c"
    },
    {
        "bug_type": "  accessing out of bounds index",
        "line": 219,
        "procedure": "unknown",
        "file": "proj_1.c"
    },
    {
        "bug_type": "  accessing out of bounds index",
        "line": 426,
        "procedure": "unknown",
        "file": "proj_1.c"
    },
    {
        "bug_type": "  signed overflow",
        "line": 452,
        "procedure": "unknown",
        "file": "proj_1.c"
    },
    {
        "bug_type": "  accessing out of bounds index",
        "line": 454,
        "procedure": "unknown",
        "file": "proj_1.c"
    },
    {
        "bug_type": "  partially overlapping lvalue assignment",
        "line": 454,
        "procedure": "unknown",
        "file": "proj_1.c"
    },
    {
        "bug_type": "  accessing uninitialized left-value",
        "line": 457,
        "procedure": "unknown",
        "file": "proj_1.c"
    },
    {
        "bug_type": "  signed overflow",
        "line": 457,
        "procedure": "unknown",
        "file": "proj_1.c"
    },
    {
        "bug_type": "  accessing out of bounds index",
        "line": 313,
        "procedure": "unknown",
        "file": "proj_1.c"
    },
    {
        "bug_type": "  accessing out of bounds index",
        "line": 339,
        "procedure": "unknown",
        "file": "proj_1.c"
    },
    {
        "bug_type": "  accessing out of bounds index",
        "line": 373,
        "procedure": "unknown",
        "file": "proj_1.c"
    },
    {
        "bug_type": "  accessing uninitialized left-value",
        "line": 382,
        "procedure": "unknown",
        "file": "proj_1.c"
    },
    {
        "bug_type": "  accessing uninitialized left-value",
        "line": 383,
        "procedure": "unknown",
        "file": "proj_1.c"
    },
    {
        "bug_type": "  accessing out of bounds index",
        "line": 110,
        "procedure": "unknown",
        "file": "proj_1.c"
    },
    {
        "bug_type": "  accessing uninitialized left-value",
        "line": 549,
        "procedure": "unknown",
        "file": "proj_1.c"
    },
    {
        "bug_type": "  accessing uninitialized left-value",
        "line": 74,
        "procedure": "unknown",
        "file": "proj_1.c"
    },
    {
        "bug_type": "  accessing uninitialized left-value",
        "line": 74,
        "procedure": "unknown",
        "file": "proj_1.c"
    },
    {
        "bug_type": "  accessing uninitialized left-value",
        "line": 472,
        "procedure": "unknown",
        "file": "proj_1.c"
    },
    {
        "bug_type": "  accessing uninitialized left-value",
        "line": 479,
        "procedure": "unknown",
        "file": "proj_1.c"
    },
    {
        "bug_type": "  accessing uninitialized left-value",
        "line": 625,
        "procedure": "unknown",
        "file": "proj_1.c"
    },
    {
        "bug_type": "  signed overflow",
        "line": 625,
        "procedure": "unknown",
        "file": "proj_1.c"
    },
    {
        "bug_type": "  accessing uninitialized left-value",
        "line": 631,
        "procedure": "unknown",
        "file": "proj_1.c"
    },
    {
        "bug_type": "  accessing out of bounds index",
        "line": 88,
        "procedure": "unknown",
        "file": "proj_1.c"
    },
    {
        "bug_type": "  accessing uninitialized left-value",
        "line": 130,
        "procedure": "unknown",
        "file": "proj_1.c"
    },
    {
        "bug_type": "  accessing uninitialized left-value",
        "line": 145,
        "procedure": "unknown",
        "file": "proj_1.c"
    },
    {
        "bug_type": "  accessing uninitialized left-value",
        "line": 151,
        "procedure": "unknown",
        "file": "proj_1.c"
    },
    {
        "bug_type": "  accessing uninitialized left-value",
        "line": 151,
        "procedure": "unknown",
        "file": "proj_1.c"
    },
    {
        "bug_type": "  accessing uninitialized left-value",
        "line": 158,
        "procedure": "unknown",
        "file": "proj_1.c"
    },
    {
        "bug_type": "  accessing uninitialized left-value",
        "line": 158,
        "procedure": "unknown",
        "file": "proj_1.c"
    },
    {
        "bug_type": "  accessing uninitialized left-value",
        "line": 165,
        "procedure": "unknown",
        "file": "proj_1.c"
    },
    {
        "bug_type": "  accessing uninitialized left-value",
        "line": 173,
        "procedure": "unknown",
        "file": "proj_1.c"
    },
    {
        "bug_type": "  accessing uninitialized left-value",
        "line": 177,
        "procedure": "unknown",
        "file": "proj_1.c"
    },
    {
        "bug_type": "  accessing uninitialized left-value",
        "line": 178,
        "procedure": "unknown",
        "file": "proj_1.c"
    },
    {
        "bug_type": "  accessing uninitialized left-value",
        "line": 188,
        "procedure": "unknown",
        "file": "proj_1.c"
    },
    {
        "bug_type": "  accessing uninitialized left-value",
        "line": 217,
        "procedure": "unknown",
        "file": "proj_1.c"
    },
    {
        "bug_type": "  accessing uninitialized left-value",
        "line": 246,
        "procedure": "unknown",
        "file": "proj_1.c"
    },
    {
        "bug_type": "  accessing uninitialized left-value",
        "line": 269,
        "procedure": "unknown",
        "file": "proj_1.c"
    },
    {
        "bug_type": "  accessing uninitialized left-value",
        "line": 276,
        "procedure": "unknown",
        "file": "proj_1.c"
    },
    {
        "bug_type": "  accessing uninitialized left-value",
        "line": 424,
        "procedure": "unknown",
        "file": "proj_1.c"
    },
    {
        "bug_type": "  accessing uninitialized left-value",
        "line": 438,
        "procedure": "unknown",
        "file": "proj_1.c"
    },
    {
        "bug_type": "  accessing uninitialized left-value",
        "line": 440,
        "procedure": "unknown",
        "file": "proj_1.c"
    },
    {
        "bug_type": "  accessing uninitialized left-value",
        "line": 452,
        "procedure": "unknown",
        "file": "proj_1.c"
    },
    {
        "bug_type": "  accessing uninitialized left-value",
        "line": 301,
        "procedure": "unknown",
        "file": "proj_1.c"
    },
    {
        "bug_type": "  accessing uninitialized left-value",
        "line": 311,
        "procedure": "unknown",
        "file": "proj_1.c"
    },
    {
        "bug_type": "  accessing uninitialized left-value",
        "line": 338,
        "procedure": "unknown",
        "file": "proj_1.c"
    },
    {
        "bug_type": "  accessing uninitialized left-value",
        "line": 371,
        "procedure": "unknown",
        "file": "proj_1.c"
    }
]